<?xml version="1.0" encoding="utf-8" ?><dwsync><file name=".DS_Store" server="ftp.rezonanta.com" local="3608089630" remote="12198020732" /><file name="ajax-email.php" server="ftp.rezonanta.com" local="3608017666" remote="12198020732" /><file name="index.html" server="ftp.rezonanta.com" local="3608090042" remote="12198021032" /><file name=".DS_Store" server="ftp.ucresearch.co.uk" local="3608887594" remote="12198819332" /><file name="ajax-email.php" server="ftp.ucresearch.co.uk" local="3608889167" remote="12198820592" /><file name="index.html" server="ftp.ucresearch.co.uk" local="3614651223" remote="12215232872" /><file name="_index.htm" server="ftp.ucresearch.co.uk" local="3525202800" remote="12204582812" /><file name="_index.htm" server="ftp.ucrgroup.co" local="3525202800" remote="12252371972" /><file name="ajax-email.php" server="ftp.ucrgroup.co" local="3608889167" remote="12252371972" /><file name="index.html" server="ftp.ucrgroup.co" local="3662706460" remote="12252645692" /></dwsync>